combogrid/__init__.py
combogrid/plot.py
combogrid-0.1.0.dist-info/LICENSE
combogrid-0.1.0.dist-info/WHEEL
combogrid-0.1.0.dist-info/METADATA
combogrid-0.1.0.dist-info/RECORD
