Metadata-Version: 2.1
Name: combogrid
Version: 0.1.0
Summary: Draw a grid of combo charts (each with a line and bars)
Home-page: https://github.com/rahimnathwani/combogrid
License: MIT
Author: Rahim Nathwani
Author-email: rahim@encona.com
Requires-Python: >=3.7.1,<4.0.0
Classifier: License :: OSI Approved :: MIT License
Classifier: Programming Language :: Python :: 3
Classifier: Programming Language :: Python :: 3.8
Classifier: Programming Language :: Python :: 3.9
Requires-Dist: matplotlib (>=3.4.1,<4.0.0)
Requires-Dist: pandas (>=1.2.4,<2.0.0)
Project-URL: Repository, https://github.com/rahimnathwani/combogrid
